{
  "contract": "Owned",
  "solidity_version": "0.4.x",
  "nodes": {
    "dfg_node_1": {
      "id": "dfg_node_1",
      "type": "contract",
      "name": "Owned",
      "data_type": null,
      "scope": "global",
      "source_location": {
        "line": 4,
        "column": 1,
        "end_line": 28,
        "end_column": 2
      },
      "properties": {
        "source_location": {
          "line": 4,
          "column": 1
        }
      }
    },
    "dfg_node_2": {
      "id": "dfg_node_2",
      "type": "state_variable",
      "name": "owner",
      "data_type": "address",
      "scope": "Owned",
      "source_location": {
        "line": 7,
        "column": 5,
        "end_line": 7,
        "end_column": 19
      },
      "properties": {
        "source_location": {
          "line": 7,
          "column": 5
        }
      }
    },
    "dfg_node_3": {
      "id": "dfg_node_3",
      "type": "constructor_function",
      "name": "Owned",
      "data_type": null,
      "scope": "Owned",
      "source_location": {
        "line": 10,
        "column": 5,
        "end_line": 12,
        "end_column": 6
      },
      "properties": {
        "source_location": {
          "line": 10,
          "column": 5
        }
      }
    },
    "dfg_node_4": {
      "id": "dfg_node_4",
      "type": "function",
      "name": "changeOwner",
      "data_type": null,
      "scope": "Owned",
      "source_location": {
        "line": 15,
        "column": 5,
        "end_line": 17,
        "end_column": 6
      },
      "properties": {
        "source_location": {
          "line": 15,
          "column": 5
        }
      }
    },
    "dfg_node_5": {
      "id": "dfg_node_5",
      "type": "function",
      "name": "kill",
      "data_type": null,
      "scope": "Owned",
      "source_location": {
        "line": 25,
        "column": 5,
        "end_line": 27,
        "end_column": 6
      },
      "properties": {
        "source_location": {
          "line": 25,
          "column": 5
        }
      }
    },
    "dfg_node_6": {
      "id": "dfg_node_6",
      "type": "contract",
      "name": "Gods",
      "data_type": null,
      "scope": "global",
      "source_location": {
        "line": 31,
        "column": 1,
        "end_line": 152,
        "end_column": 2
      },
      "properties": {
        "source_location": {
          "line": 31,
          "column": 1
        }
      }
    },
    "dfg_node_7": {
      "id": "dfg_node_7",
      "type": "state_variable",
      "name": "members",
      "data_type": "Member[]",
      "scope": "Gods",
      "source_location": {
        "line": 48,
        "column": 5,
        "end_line": 48,
        "end_column": 29
      },
      "properties": {
        "source_location": {
          "line": 48,
          "column": 5
        }
      }
    },
    "dfg_node_8": {
      "id": "dfg_node_8",
      "type": "state_variable",
      "name": "memberId",
      "data_type": "mapping (address => uint)",
      "scope": "Gods",
      "source_location": {
        "line": 51,
        "column": 5,
        "end_line": 51,
        "end_column": 47
      },
      "properties": {
        "source_location": {
          "line": 51,
          "column": 5
        }
      }
    },
    "dfg_node_9": {
      "id": "dfg_node_9",
      "type": "state_variable",
      "name": "pks",
      "data_type": "mapping (uint => string)",
      "scope": "Gods",
      "source_location": {
        "line": 54,
        "column": 5,
        "end_line": 54,
        "end_column": 41
      },
      "properties": {
        "source_location": {
          "line": 54,
          "column": 5
        }
      }
    },
    "dfg_node_10": {
      "id": "dfg_node_10",
      "type": "state_variable",
      "name": "memberData",
      "data_type": "mapping (uint => string)",
      "scope": "Gods",
      "source_location": {
        "line": 57,
        "column": 5,
        "end_line": 57,
        "end_column": 48
      },
      "properties": {
        "source_location": {
          "line": 57,
          "column": 5
        }
      }
    },
    "dfg_node_11": {
      "id": "dfg_node_11",
      "type": "constructor_function",
      "name": "Gods",
      "data_type": null,
      "scope": "Gods",
      "source_location": {
        "line": 66,
        "column": 5,
        "end_line": 69,
        "end_column": 6
      },
      "properties": {
        "source_location": {
          "line": 66,
          "column": 5
        }
      }
    },
    "dfg_node_12": {
      "id": "dfg_node_12",
      "type": "function",
      "name": "addMember",
      "data_type": null,
      "scope": "Gods",
      "source_location": {
        "line": 76,
        "column": 5,
        "end_line": 119,
        "end_column": 6
      },
      "properties": {
        "source_location": {
          "line": 76,
          "column": 5
        }
      }
    },
    "dfg_node_13": {
      "id": "dfg_node_13",
      "type": "function",
      "name": "getPK",
      "data_type": null,
      "scope": "Gods",
      "source_location": {
        "line": 122,
        "column": 5,
        "end_line": 124,
        "end_column": 6
      },
      "properties": {
        "source_location": {
          "line": 122,
          "column": 5
        }
      }
    },
    "dfg_node_15": {
      "id": "dfg_node_15",
      "type": "parameter",
      "name": "param_13",
      "data_type": "string",
      "scope": "getPK_function",
      "source_location": null,
      "properties": {
        "is_return": true,
        "function": "getPK"
      }
    },
    "dfg_node_16": {
      "id": "dfg_node_16",
      "type": "function",
      "name": "getMemberCount",
      "data_type": null,
      "scope": "Gods",
      "source_location": {
        "line": 127,
        "column": 5,
        "end_line": 129,
        "end_column": 6
      },
      "properties": {
        "source_location": {
          "line": 127,
          "column": 5
        }
      }
    },
    "dfg_node_18": {
      "id": "dfg_node_18",
      "type": "parameter",
      "name": "param_16",
      "data_type": "uint",
      "scope": "getMemberCount_function",
      "source_location": null,
      "properties": {
        "is_return": true,
        "function": "getMemberCount"
      }
    },
    "dfg_node_19": {
      "id": "dfg_node_19",
      "type": "function",
      "name": "getMember",
      "data_type": null,
      "scope": "Gods",
      "source_location": {
        "line": 133,
        "column": 5,
        "end_line": 151,
        "end_column": 6
      },
      "properties": {
        "source_location": {
          "line": 133,
          "column": 5
        }
      }
    },
    "dfg_node_21": {
      "id": "dfg_node_21",
      "type": "parameter",
      "name": "name",
      "data_type": "string",
      "scope": "getMember_function",
      "source_location": null,
      "properties": {
        "is_return": true,
        "function": "getMember"
      }
    },
    "dfg_node_23": {
      "id": "dfg_node_23",
      "type": "parameter",
      "name": "surname",
      "data_type": "string",
      "scope": "getMember_function",
      "source_location": null,
      "properties": {
        "is_return": true,
        "function": "getMember"
      }
    },
    "dfg_node_25": {
      "id": "dfg_node_25",
      "type": "parameter",
      "name": "patronymic",
      "data_type": "string",
      "scope": "getMember_function",
      "source_location": null,
      "properties": {
        "is_return": true,
        "function": "getMember"
      }
    },
    "dfg_node_27": {
      "id": "dfg_node_27",
      "type": "parameter",
      "name": "birthDate",
      "data_type": "uint",
      "scope": "getMember_function",
      "source_location": null,
      "properties": {
        "is_return": true,
        "function": "getMember"
      }
    },
    "dfg_node_29": {
      "id": "dfg_node_29",
      "type": "parameter",
      "name": "birthPlace",
      "data_type": "string",
      "scope": "getMember_function",
      "source_location": null,
      "properties": {
        "is_return": true,
        "function": "getMember"
      }
    },
    "dfg_node_31": {
      "id": "dfg_node_31",
      "type": "parameter",
      "name": "avatarHash",
      "data_type": "string",
      "scope": "getMember_function",
      "source_location": null,
      "properties": {
        "is_return": true,
        "function": "getMember"
      }
    },
    "dfg_node_33": {
      "id": "dfg_node_33",
      "type": "parameter",
      "name": "avatarID",
      "data_type": "uint",
      "scope": "getMember_function",
      "source_location": null,
      "properties": {
        "is_return": true,
        "function": "getMember"
      }
    },
    "dfg_node_35": {
      "id": "dfg_node_35",
      "type": "parameter",
      "name": "data",
      "data_type": "string",
      "scope": "getMember_function",
      "source_location": null,
      "properties": {
        "is_return": true,
        "function": "getMember"
      }
    }
  },
  "edges": {
    "dfg_edge_1": {
      "id": "dfg_edge_1",
      "source": "dfg_node_1",
      "target": "dfg_node_2",
      "type": "definition",
      "label": null,
      "weight": 1,
      "properties": {}
    },
    "dfg_edge_2": {
      "id": "dfg_edge_2",
      "source": "dfg_node_1",
      "target": "dfg_node_3",
      "type": "definition",
      "label": null,
      "weight": 1,
      "properties": {}
    },
    "dfg_edge_3": {
      "id": "dfg_edge_3",
      "source": "dfg_node_1",
      "target": "dfg_node_4",
      "type": "definition",
      "label": null,
      "weight": 1,
      "properties": {}
    },
    "dfg_edge_4": {
      "id": "dfg_edge_4",
      "source": "dfg_node_1",
      "target": "dfg_node_5",
      "type": "definition",
      "label": null,
      "weight": 1,
      "properties": {}
    },
    "dfg_edge_5": {
      "id": "dfg_edge_5",
      "source": "dfg_node_6",
      "target": "dfg_node_7",
      "type": "definition",
      "label": null,
      "weight": 1,
      "properties": {}
    },
    "dfg_edge_6": {
      "id": "dfg_edge_6",
      "source": "dfg_node_6",
      "target": "dfg_node_8",
      "type": "definition",
      "label": null,
      "weight": 1,
      "properties": {}
    },
    "dfg_edge_7": {
      "id": "dfg_edge_7",
      "source": "dfg_node_6",
      "target": "dfg_node_9",
      "type": "definition",
      "label": null,
      "weight": 1,
      "properties": {}
    },
    "dfg_edge_8": {
      "id": "dfg_edge_8",
      "source": "dfg_node_6",
      "target": "dfg_node_10",
      "type": "definition",
      "label": null,
      "weight": 1,
      "properties": {}
    },
    "dfg_edge_9": {
      "id": "dfg_edge_9",
      "source": "dfg_node_6",
      "target": "dfg_node_11",
      "type": "definition",
      "label": null,
      "weight": 1,
      "properties": {}
    },
    "dfg_edge_10": {
      "id": "dfg_edge_10",
      "source": "dfg_node_6",
      "target": "dfg_node_12",
      "type": "definition",
      "label": null,
      "weight": 1,
      "properties": {}
    },
    "dfg_edge_11": {
      "id": "dfg_edge_11",
      "source": "dfg_node_13",
      "target": "dfg_node_15",
      "type": "definition",
      "label": null,
      "weight": 1,
      "properties": {}
    },
    "dfg_edge_12": {
      "id": "dfg_edge_12",
      "source": "dfg_node_6",
      "target": "dfg_node_13",
      "type": "definition",
      "label": null,
      "weight": 1,
      "properties": {}
    },
    "dfg_edge_13": {
      "id": "dfg_edge_13",
      "source": "dfg_node_16",
      "target": "dfg_node_18",
      "type": "definition",
      "label": null,
      "weight": 1,
      "properties": {}
    },
    "dfg_edge_14": {
      "id": "dfg_edge_14",
      "source": "dfg_node_6",
      "target": "dfg_node_16",
      "type": "definition",
      "label": null,
      "weight": 1,
      "properties": {}
    },
    "dfg_edge_15": {
      "id": "dfg_edge_15",
      "source": "dfg_node_19",
      "target": "dfg_node_21",
      "type": "definition",
      "label": null,
      "weight": 1,
      "properties": {}
    },
    "dfg_edge_16": {
      "id": "dfg_edge_16",
      "source": "dfg_node_19",
      "target": "dfg_node_23",
      "type": "definition",
      "label": null,
      "weight": 1,
      "properties": {}
    },
    "dfg_edge_17": {
      "id": "dfg_edge_17",
      "source": "dfg_node_19",
      "target": "dfg_node_25",
      "type": "definition",
      "label": null,
      "weight": 1,
      "properties": {}
    },
    "dfg_edge_18": {
      "id": "dfg_edge_18",
      "source": "dfg_node_19",
      "target": "dfg_node_27",
      "type": "definition",
      "label": null,
      "weight": 1,
      "properties": {}
    },
    "dfg_edge_19": {
      "id": "dfg_edge_19",
      "source": "dfg_node_19",
      "target": "dfg_node_29",
      "type": "definition",
      "label": null,
      "weight": 1,
      "properties": {}
    },
    "dfg_edge_20": {
      "id": "dfg_edge_20",
      "source": "dfg_node_19",
      "target": "dfg_node_31",
      "type": "definition",
      "label": null,
      "weight": 1,
      "properties": {}
    },
    "dfg_edge_21": {
      "id": "dfg_edge_21",
      "source": "dfg_node_19",
      "target": "dfg_node_33",
      "type": "definition",
      "label": null,
      "weight": 1,
      "properties": {}
    },
    "dfg_edge_22": {
      "id": "dfg_edge_22",
      "source": "dfg_node_19",
      "target": "dfg_node_35",
      "type": "definition",
      "label": null,
      "weight": 1,
      "properties": {}
    },
    "dfg_edge_23": {
      "id": "dfg_edge_23",
      "source": "dfg_node_6",
      "target": "dfg_node_19",
      "type": "definition",
      "label": null,
      "weight": 1,
      "properties": {}
    }
  },
  "metadata": {
    "index": 1294,
    "source_line": 1295,
    "label": 0,
    "mode": "compact",
    "contract_name": "Owned",
    "timestamp": "20251029_142838"
  },
  "label": 0
}